{
  "errorcode": 0, 
  "errormsg": "OK", 
  "tags": [
    {
      "confidence": 0.7705640196800232, 
      "idx": "723", 
      "color": "银灰", 
      "brand": "五菱汽车", 
      "serial": "五菱之光#2010款", 
      "type": "微面"
    }, 
    {
      "confidence": 0.10433100163936615, 
      "idx": "723", 
      "color": "银灰", 
      "brand": "五菱汽车", 
      "serial": "五菱之光#2013款", 
      "type": "微面"
    }, 
    {
      "confidence": 0.072332002222538, 
      "idx": "723", 
      "color": "银灰", 
      "brand": "五菱汽车", 
      "serial": "五菱之光#2008款", 
      "type": "微面"
    }, 
    {
      "confidence": 0.0065291100181639194, 
      "idx": "723", 
      "color": "银灰", 
      "brand": "五菱汽车", 
      "serial": "五菱之光#2014款", 
      "type": "微面"
    }, 
    {
      "confidence": 0.004900630097836256, 
      "idx": "992", 
      "color": "银灰", 
      "brand": "长安汽车", 
      "serial": "长安之星#2009款", 
      "type": "微面"
    }
  ], 
  "logo_coord": [], 
  "car_coord": {
    "y": 50.0, 
    "x": 494.0, 
    "height": 844.0, 
    "width": 692.0
  }
}