{
  "errorcode": 0, 
  "errormsg": "OK", 
  "tags": [
    {
      "confidence": 0.4611090123653412, 
      "idx": "173", 
      "color": "银灰", 
      "brand": "别克", 
      "serial": "凯越#2008款", 
      "type": "紧凑型车"
    }, 
    {
      "confidence": 0.28615400195121765, 
      "idx": "173", 
      "color": "银灰", 
      "brand": "别克", 
      "serial": "凯越#2016款", 
      "type": "紧凑型车"
    }, 
    {
      "confidence": 0.17410500347614288, 
      "idx": "173", 
      "color": "银灰", 
      "brand": "别克", 
      "serial": "凯越#2011款", 
      "type": "紧凑型车"
    }, 
    {
      "confidence": 0.015110299922525883, 
      "idx": "116", 
      "color": "银灰", 
      "brand": "华晨中华", 
      "serial": "中华骏捷#2009款", 
      "type": "中型车"
    }, 
    {
      "confidence": 0.011897999793291092, 
      "idx": "342", 
      "color": "银灰", 
      "brand": "欧宝", 
      "serial": "赛飞利", 
      "type": "MPV"
    }
  ], 
  "logo_coord": [], 
  "car_coord": {
    "y": 264.0, 
    "x": 517.0, 
    "height": 680.0, 
    "width": 684.0
  }
}