{
  "errorcode": 0, 
  "errormsg": "OK", 
  "tags": [
    {
      "confidence": 0.1466509997844696, 
      "idx": "-1", 
      "color": "黑", 
      "brand": "丰田(进口)", 
      "serial": "卡罗拉(海外)", 
      "type": "紧凑型车"
    }, 
    {
      "confidence": 0.10840500146150589, 
      "idx": "526", 
      "color": "黑", 
      "brand": "猎豹汽车", 
      "serial": "黑金刚", 
      "type": "SUV"
    }, 
    {
      "confidence": 0.07653249800205231, 
      "idx": "312", 
      "color": "黑", 
      "brand": "雷克萨斯", 
      "serial": "雷克萨斯LX", 
      "type": "大型SUV"
    }, 
    {
      "confidence": 0.07596299797296524, 
      "idx": "769", 
      "color": "黑", 
      "brand": "北汽制造", 
      "serial": "陆霸", 
      "type": "SUV"
    }, 
    {
      "confidence": 0.04947200044989586, 
      "idx": "-1", 
      "color": "黑", 
      "brand": "萨博", 
      "serial": "Saab_9000", 
      "type": "中大型车"
    }
  ], 
  "logo_coord": [], 
  "car_coord": {
    "y": 291.0, 
    "x": 430.0, 
    "height": 732.0, 
    "width": 786.0
  }
}