{
  "errorcode": 0, 
  "errormsg": "OK", 
  "tags": [
    {
      "confidence": 0.5901039838790894, 
      "idx": "723", 
      "color": "银灰", 
      "brand": "五菱汽车", 
      "serial": "五菱之光#2010款", 
      "type": "微面"
    }, 
    {
      "confidence": 0.17059800028800964, 
      "idx": "723", 
      "color": "银灰", 
      "brand": "五菱汽车", 
      "serial": "五菱之光#2013款", 
      "type": "微面"
    }, 
    {
      "confidence": 0.06894019991159439, 
      "idx": "723", 
      "color": "银灰", 
      "brand": "五菱汽车", 
      "serial": "五菱之光#2008款", 
      "type": "微面"
    }, 
    {
      "confidence": 0.06647519767284393, 
      "idx": "992", 
      "color": "银灰", 
      "brand": "长安汽车", 
      "serial": "长安之星#2009款", 
      "type": "微面"
    }, 
    {
      "confidence": 0.017643200233578682, 
      "idx": "723", 
      "color": "银灰", 
      "brand": "五菱汽车", 
      "serial": "五菱之光#2014款", 
      "type": "微面"
    }
  ], 
  "logo_coord": [], 
  "car_coord": {
    "y": 344.0, 
    "x": 405.0, 
    "height": 540.0, 
    "width": 489.0
  }
}