{
  "errorcode": 0, 
  "errormsg": "OK", 
  "tags": [
    {
      "confidence": 0.4879109859466553, 
      "idx": "440", 
      "color": "棕", 
      "brand": "沃尔沃", 
      "serial": "沃尔沃XC60(进口)#2009款", 
      "type": "中型SUV"
    }, 
    {
      "confidence": 0.14558200538158417, 
      "idx": "440", 
      "color": "棕", 
      "brand": "沃尔沃", 
      "serial": "沃尔沃XC60(进口)#2012款", 
      "type": "中型SUV"
    }, 
    {
      "confidence": 0.1188649982213974, 
      "idx": "440", 
      "color": "棕", 
      "brand": "沃尔沃", 
      "serial": "沃尔沃XC60(进口)#2011款", 
      "type": "中型SUV"
    }, 
    {
      "confidence": 0.061051998287439346, 
      "idx": "377", 
      "color": "棕", 
      "brand": "沃尔沃", 
      "serial": "沃尔沃C70", 
      "type": "跑车"
    }, 
    {
      "confidence": 0.05374529957771301, 
      "idx": "440", 
      "color": "棕", 
      "brand": "沃尔沃", 
      "serial": "沃尔沃XC60(进口)#2016款", 
      "type": "中型SUV"
    }
  ], 
  "logo_coord": [], 
  "car_coord": {
    "y": 209.0, 
    "x": 473.0, 
    "height": 667.0, 
    "width": 576.0
  }
}